power_profiler.py
ppk2_api/__init__.py
ppk2_api/ppk2_api.py
ppk2_api-0.9.2.dist-info/LICENSE.md
ppk2_api-0.9.2.dist-info/METADATA
ppk2_api-0.9.2.dist-info/WHEEL
ppk2_api-0.9.2.dist-info/top_level.txt
ppk2_api-0.9.2.dist-info/RECORD
